LICENSE
README.md
pyproject.toml
codealchemy/__init__.py
codealchemy/code_decorators.py
codealchemy/log_decorators.py
codealchemy/utils/__init__.py
codealchemy/utils/kafkaUtils/__init__.py
codealchemy/utils/kafkaUtils/kafka_consumer.py
codealchemy/utils/kafkaUtils/kafka_producer.py
codealchemy-1.2.6.dist-info/METADATA
codealchemy-1.2.6.dist-info/WHEEL
codealchemy-1.2.6.dist-info/licenses/LICENSE
codealchemy-1.2.6.dist-info/RECORD
