Metadata-Version: 2.3
Name: codealchemy
Version: 1.2.6
Summary: CodeAlchemy is a Python package that provides utility and decorators for development.
Project-URL: Homepage, https://github.com/GirishCodeAlchemy/codealchemy
Project-URL: Issues, https://github.com/GirishCodeAlchemy/codealchemy/issues
Author-email: GirishCodeAlchemy <girishcodealchemy@gmail.com>
License: MIT
Classifier: Intended Audience :: Developers
Classifier: License :: OSI Approved :: MIT License
Classifier: Operating System :: OS Independent
Classifier: Programming Language :: Python :: 3
Classifier: Topic :: Software Development :: Build Tools
Requires-Python: >=3.6
Requires-Dist: confluent-kafka==2.6.0
Requires-Dist: requests==2.32.3
Requires-Dist: tabulate==0.9.0
Provides-Extra: docs
